README.rst
setup.py
django_pgroonga/__init__.py
django_pgroonga.egg-info/PKG-INFO
django_pgroonga.egg-info/SOURCES.txt
django_pgroonga.egg-info/dependency_links.txt
django_pgroonga.egg-info/top_level.txt