Metadata-Version: 1.1
Name: django-pgroonga
Version: 0.0.1
Summary: PGroonga utility for Django.
Home-page: https://github.com/atsuoishimoto/django-pgroonga
Author: Atsuo Ishimoto
Author-email: ishimoto@gembook.org
License: MIT
Keywords: django groonga pgroonga
Platform: UNKNOWN
Classifier: Programming Language :: Python :: 3
Classifier: Development Status :: 3 - Alpha
Classifier: Framework :: Django
